COPYING
MANIFEST.in
README.mdown
setup.cfg
setup.py
django_json_rpc.egg-info/PKG-INFO
django_json_rpc.egg-info/SOURCES.txt
django_json_rpc.egg-info/dependency_links.txt
django_json_rpc.egg-info/not-zip-safe
django_json_rpc.egg-info/requires.txt
django_json_rpc.egg-info/top_level.txt
jsonrpc/__init__.py
jsonrpc/_json.py
jsonrpc/_types.py
jsonrpc/exceptions.py
jsonrpc/mochikit.py
jsonrpc/proxy.py
jsonrpc/site.py
jsonrpc/views.py
jsonrpc/templates/browse.html
test/test.py